extracontext/__init__.py
extracontext/_future_task.py
extracontext/base.py
extracontext/contextlocal.py
extracontext/contextlocal_native.py
extracontext/executor.py
extracontext/mapping.py
python_extracontext-1.1.1.dist-info/LICENSE
python_extracontext-1.1.1.dist-info/METADATA
python_extracontext-1.1.1.dist-info/WHEEL
python_extracontext-1.1.1.dist-info/top_level.txt
python_extracontext-1.1.1.dist-info/RECORD
